setup.py
src/rore/__init__.py
src/rore/shell.py
src/rore.egg-info/PKG-INFO
src/rore.egg-info/SOURCES.txt
src/rore.egg-info/dependency_links.txt
src/rore.egg-info/entry_points.txt
src/rore.egg-info/not-zip-safe
src/rore.egg-info/requires.txt
src/rore.egg-info/top_level.txt