Metadata-Version: 1.0
Name: rore
Version: 0.7
Summary: A command line utility for Redmine
Home-page: https://github.com/rackerlabs/rore
Author: Jesse Keating
Author-email: jesse.keating@rackspace.com
License: Apache 2.0
Platform: UNKNOWN
